gaget/VERSION
gaget/__init__.py
gaget/gaget.py
gaget-0.1.1.dist-info/METADATA
gaget-0.1.1.dist-info/WHEEL
gaget-0.1.1.dist-info/entry_points.txt
gaget-0.1.1.dist-info/top_level.txt
gaget-0.1.1.dist-info/RECORD
