Metadata-Version: 2.1
Name: gaget
Version: 0.1.1
Summary: Download customer data
Home-page: https://github.com/ConductorTechnologies/gaget
Author: Julian Mann
Author-email: julian@conductortech.com
License: UNKNOWN
Platform: UNKNOWN
Classifier: Operating System :: OS Independent
Classifier: Programming Language :: Python :: 3.7
Classifier: Programming Language :: Python
Requires-Python: ~=3.7
Requires-Dist: boto3 (<2.0.0,>=1.14.0)
Requires-Dist: google-cloud-datastore (<2.0.0,>=1.13.0)
Requires-Dist: google-cloud-storage (<2.0.0,>=1.29.0)
